README.md
setup.cfg
setup.py
imodb.egg-info/PKG-INFO
imodb.egg-info/SOURCES.txt
imodb.egg-info/dependency_links.txt
imodb.egg-info/top_level.txt
src/imodb/__init__.py
test/test_models.py