Metadata-Version: 1.1
Name: imodb
Version: 0.1.0
Summary: IMODB - In-Memory Object Database
Home-page: https://github.com/aryzhov/python-imodb
Author: Alexander Ryzhov
Author-email: aryzhov07@gmail.com
License: MIT
Keywords: python memory object database
Platform: UNKNOWN
Classifier: Development Status :: 3 - Alpha
Classifier: License :: OSI Approved :: MIT License
Classifier: Topic :: Software Development :: Libraries :: Python Modules
Classifier: Operating System :: OS Independent
Classifier: Programming Language :: Python :: 3
